getANS/__init__.py
getANS/__main__.py
getANS/_ans_api.py
getANS/_assignment_db.py
getANS/_misc.py
getANS/_request_tools.py
getANS/_token.py
getANS/cli.py
getANS/types/__init__.py
getANS/types/ans_types.py
getANS/types/list_of_dicts.py
getans-0.9.2.dist-info/LICENSE
getans-0.9.2.dist-info/WHEEL
getans-0.9.2.dist-info/METADATA
getans-0.9.2.dist-info/RECORD
