Metadata-Version: 2.3
Name: getANS
Version: 0.9.2
Summary: Retrieving Data from ANS with Python
Author-email: Oliver Lindemann <lindemann@essb.eur.nl>
Requires-Python: >=3.10
Classifier: License :: OSI Approved :: MIT License
Requires-Dist: pandas>=2.2
Requires-Dist: appdirs>=1.4
Requires-Dist: requests>=2.32
Requires-Dist: pytest >=2.7.3 ; extra == "test"
Project-URL: Documentation, https://github.com/essb-mt-section/getANS
Project-URL: Source, https://github.com/essb-mt-section/getANS
Provides-Extra: test
